ombott/__init__.py
ombott/common_helpers.py
ombott/error.html
ombott/error_render.py
ombott/errors.py
ombott/mixable.py
ombott/ombott.py
ombott/response.py
ombott/server_adapters.py
ombott/static_stream.py
ombott/request_pkg/__init__.py
ombott/request_pkg/body_mixin.py
ombott/request_pkg/errors.py
ombott/request_pkg/helpers.py
ombott/request_pkg/multipart.py
ombott/request_pkg/props_mixin.py
ombott/request_pkg/request.py
ombott/router/__init__.py
ombott/router/errors.py
ombott/router/filter_factory.py
ombott/router/parser.py
ombott/router/radidict.py
ombott/router/radirouter.py
ombott/router/sym_stream.py
tests/__init__.py
tests/test_simple_config.py
tests/request/__init__.py
tests/request/__test_thread_crossref.py
tests/request/test_body_read.py
tests/request/test_helpers.py
tests/request/test_multipart.py
tests/request/test_props.py
tests/request/test_thread.py
tests/response/__init__.py
tests/response/test_static_file.py
tests/response/test_thread.py
tests/router/__init__.py
tests/router/test_route.py
tests/router/test_router.py
ombott-2.3.dist-info/LICENSE
ombott-2.3.dist-info/METADATA
ombott-2.3.dist-info/WHEEL
ombott-2.3.dist-info/top_level.txt
ombott-2.3.dist-info/RECORD
