Metadata-Version: 2.1
Name: ombott
Version: 2.3
Summary: One More BOTTle
Home-page: https://github.com/valq7711/ombott
Author: Valery Kucherov <valq7711@gmail.com>
Author-email: valq7711@gmail.com
Maintainer: Valery Kucherov <valq7711@gmail.com>
Maintainer-email: valq7711@gmail.com
License: MIT
Keywords: python webapplication
Platform: any
Classifier: Development Status :: 3 - Alpha
Classifier: Environment :: Web Environment
Classifier: Intended Audience :: Developers
Classifier: License :: OSI Approved :: MIT License
Classifier: Operating System :: OS Independent
Classifier: Programming Language :: Python :: 3.7
Classifier: Programming Language :: Python :: 3.8
Classifier: Programming Language :: Python :: 3.9
Classifier: Programming Language :: Python :: 3.10
Classifier: Topic :: Internet :: WWW/HTTP :: HTTP Servers
Classifier: Topic :: Software Development :: Libraries :: Python Modules
Requires-Python: >=3.7
License-File: LICENSE
